{"openapi":"3.0.0","info":{"title":"backendinsuranceweb","version":"0.0.1","description":"backendinsuranceweb","contact":{"name":"feartheoldblood1","email":"p_lobachev@inbox.ru"}},"paths":{"/ipoteka/{bank}/{remains}/{insuranceObject}/{propertyHouse}/{name}/{dateBirth}/{phoneNumber}/{email}":{"post":{"x-controller-name":"IpotekaController","x-operation-name":"sendMsgToMail","tags":["IpotekaController"],"responses":{"200":{"description":"Ipoteka model instance","content":{"application/json":{"schema":{"$ref":"#/components/schemas/Ipoteka"}}}}},"parameters":[{"name":"bank","in":"path","schema":{"type":"string"},"required":true},{"name":"remains","in":"path","schema":{"type":"string"},"required":true},{"name":"insuranceObject","in":"path","schema":{"type":"string"},"required":true},{"name":"propertyHouse","in":"path","schema":{"type":"string"},"required":true},{"name":"name","in":"path","schema":{"type":"string"},"required":true},{"name":"dateBirth","in":"path","schema":{"type":"string"},"required":true},{"name":"phoneNumber","in":"path","schema":{"type":"string"},"required":true},{"name":"email","in":"path","schema":{"type":"string"},"required":true}],"operationId":"IpotekaController.sendMsgToMail"}},"/journey/{countries}/{dateStart}/{dateEnd}/{ageRange}/{citezenship}/{email}":{"post":{"x-controller-name":"JourneyController","x-operation-name":"sendMsgToMail","tags":["JourneyController"],"responses":{"200":{"description":"Ipoteka model instance","content":{"application/json":{"schema":{"$ref":"#/components/schemas/Ipoteka"}}}}},"parameters":[{"name":"countries","in":"path","schema":{"type":"string"},"required":true},{"name":"dateStart","in":"path","schema":{"type":"string"},"required":true},{"name":"dateEnd","in":"path","schema":{"type":"string"},"required":true},{"name":"ageRange","in":"path","schema":{"type":"string"},"required":true},{"name":"citezenship","in":"path","schema":{"type":"string"},"required":true},{"name":"email","in":"path","schema":{"type":"string"},"required":true}],"operationId":"JourneyController.sendMsgToMail"}},"/kasko/{registrAddress}/{markaCar}/{markaModelClass}/{dateCar}/{engineCapacity}/{bank}/{carCost}/{carPlace}/{userData}/{name}/{phone}":{"post":{"x-controller-name":"KaskoController","x-operation-name":"sendMsgToMail","tags":["KaskoController"],"responses":{"200":{"description":"Ipoteka model instance","content":{"application/json":{"schema":{"$ref":"#/components/schemas/Ipoteka"}}}}},"parameters":[{"name":"registrAddress","in":"path","schema":{"type":"string"},"required":true},{"name":"markaCar","in":"path","schema":{"type":"string"},"required":true},{"name":"markaModelClass","in":"path","schema":{"type":"string"},"required":true},{"name":"dateCar","in":"path","schema":{"type":"string"},"required":true},{"name":"engineCapacity","in":"path","schema":{"type":"string"},"required":true},{"name":"bank","in":"path","schema":{"type":"string"},"required":true},{"name":"carCost","in":"path","schema":{"type":"string"},"required":true},{"name":"carPlace","in":"path","schema":{"type":"string"},"required":true},{"name":"userData","in":"path","schema":{"type":"string"},"required":true},{"name":"name","in":"path","schema":{"type":"string"},"required":true},{"name":"phone","in":"path","schema":{"type":"string"},"required":true}],"operationId":"KaskoController.sendMsgToMail"}},"/legalentity/{companyName}/{addres}/{INN}/{region}/{surname}/{name}/{otchestvo}/{email}/{phone}":{"post":{"x-controller-name":"LegelentityController","x-operation-name":"sendMsgToMail","tags":["LegelentityController"],"responses":{"200":{"description":"Ipoteka model instance","content":{"application/json":{"schema":{"$ref":"#/components/schemas/Ipoteka"}}}}},"parameters":[{"name":"companyName","in":"path","schema":{"type":"string"},"required":true},{"name":"addres","in":"path","schema":{"type":"string"},"required":true},{"name":"INN","in":"path","schema":{"type":"string"},"required":true},{"name":"region","in":"path","schema":{"type":"string"},"required":true},{"name":"surname","in":"path","schema":{"type":"string"},"required":true},{"name":"name","in":"path","schema":{"type":"string"},"required":true},{"name":"otchestvo","in":"path","schema":{"type":"string"},"required":true},{"name":"email","in":"path","schema":{"type":"string"},"required":true},{"name":"phone","in":"path","schema":{"type":"string"},"required":true}],"operationId":"LegelentityController.sendMsgToMail"}},"/ping":{"get":{"x-controller-name":"PingController","x-operation-name":"ping","tags":["PingController"],"responses":{"200":{"description":"Ping Response","content":{"application/json":{"schema":{"$ref":"#/components/schemas/PingResponse"}}}}},"operationId":"PingController.ping"}},"/users/count":{"get":{"x-controller-name":"UserController","x-operation-name":"count","tags":["UserController"],"responses":{"200":{"description":"User model count","content":{"application/json":{"schema":{"$ref":"#/components/schemas/loopback.Count"}}}}},"parameters":[{"name":"where","in":"query","content":{"application/json":{"schema":{"type":"object","title":"User.WhereFilter","additionalProperties":true,"x-typescript-type":"@loopback/repository#Where<User>"}}}}],"operationId":"UserController.count"}},"/users/{mail}/{phone_number}/{password}/{surname}/{name}/{otchestvo}/{datebirth}/{foreigner}/{document}/{document_number}/{document_series}":{"post":{"x-controller-name":"UserController","x-operation-name":"create","tags":["UserController"],"responses":{"200":{"description":"User model instance","content":{"application/json":{"schema":{"$ref":"#/components/schemas/User"}}}}},"parameters":[{"name":"mail","in":"path","schema":{"type":"string"},"required":true},{"name":"phone_number","in":"path","schema":{"type":"string"},"required":true},{"name":"password","in":"path","schema":{"type":"string","format":"password"},"required":true},{"name":"surname","in":"path","schema":{"type":"string"},"required":true},{"name":"name","in":"path","schema":{"type":"string"},"required":true},{"name":"otchestvo","in":"path","schema":{"type":"string"},"required":true},{"name":"datebirth","in":"path","schema":{"type":"string","format":"date"},"required":true},{"name":"foreigner","in":"path","schema":{"type":"string"},"required":true},{"name":"document","in":"path","schema":{"type":"string"},"required":true},{"name":"document_number","in":"path","schema":{"type":"string"},"required":true},{"name":"document_series","in":"path","schema":{"type":"string"},"required":true}],"operationId":"UserController.create"}},"/users/{email}/{password}":{"get":{"x-controller-name":"UserController","x-operation-name":"findByNamePass","tags":["UserController"],"responses":{"200":{"description":"Array of User model instances","content":{"application/json":{"schema":{"type":"array","items":{"$ref":"#/components/schemas/UserWithRelations"}}}}}},"parameters":[{"name":"email","in":"path","schema":{"type":"string"},"required":true},{"name":"password","in":"path","schema":{"type":"string","format":"password"},"required":true}],"operationId":"UserController.findByNamePass"}},"/users/{id}":{"put":{"x-controller-name":"UserController","x-operation-name":"replaceById","tags":["UserController"],"responses":{"204":{"description":"No Content","content":{"application/json":{"schema":{"description":"User PUT success"}}}}},"parameters":[{"name":"id","in":"path","schema":{"type":"number"},"required":true}],"requestBody":{"content":{"application/json":{"schema":{"$ref":"#/components/schemas/User"}}},"x-parameter-index":1},"operationId":"UserController.replaceById"},"patch":{"x-controller-name":"UserController","x-operation-name":"updateById","tags":["UserController"],"responses":{"204":{"description":"No Content","content":{"application/json":{"schema":{"description":"User PATCH success"}}}}},"parameters":[{"name":"id","in":"path","schema":{"type":"number"},"required":true}],"requestBody":{"content":{"application/json":{"schema":{"$ref":"#/components/schemas/UserPartial"}}},"x-parameter-index":1},"operationId":"UserController.updateById"},"get":{"x-controller-name":"UserController","x-operation-name":"findById","tags":["UserController"],"responses":{"200":{"description":"User model instance","content":{"application/json":{"schema":{"$ref":"#/components/schemas/UserWithRelations"}}}}},"parameters":[{"name":"id","in":"path","schema":{"type":"number"},"required":true},{"name":"filter","in":"query","content":{"application/json":{"schema":{"$ref":"#/components/schemas/User.Filter"}}}}],"operationId":"UserController.findById"},"delete":{"x-controller-name":"UserController","x-operation-name":"deleteById","tags":["UserController"],"responses":{"204":{"description":"No Content","content":{"application/json":{"schema":{"description":"User DELETE success"}}}}},"parameters":[{"name":"id","in":"path","schema":{"type":"number"},"required":true}],"operationId":"UserController.deleteById"}},"/users":{"patch":{"x-controller-name":"UserController","x-operation-name":"updateAll","tags":["UserController"],"responses":{"200":{"description":"User PATCH success count","content":{"application/json":{"schema":{"$ref":"#/components/schemas/loopback.Count"}}}}},"parameters":[{"name":"where","in":"query","content":{"application/json":{"schema":{"type":"object","title":"User.WhereFilter","additionalProperties":true,"x-typescript-type":"@loopback/repository#Where<User>"}}}}],"requestBody":{"content":{"application/json":{"schema":{"$ref":"#/components/schemas/UserPartial"}}}},"operationId":"UserController.updateAll"},"get":{"x-controller-name":"UserController","x-operation-name":"find","tags":["UserController"],"responses":{"200":{"description":"Array of User model instances","content":{"application/json":{"schema":{"type":"array","items":{"$ref":"#/components/schemas/UserWithRelations"}}}}}},"parameters":[{"name":"filter","in":"query","content":{"application/json":{"schema":{"$ref":"#/components/schemas/User.Filter1"}}}}],"operationId":"UserController.find"}}},"servers":[{"url":"http://192.168.0.104:3000"}],"components":{"schemas":{"Ipoteka":{"title":"Ipoteka","type":"object","properties":{"id":{"type":"number"},"bank":{"type":"string"},"moneyDuty":{"type":"string"},"lifeOrHouse":{"type":"string"},"apartment":{"type":"string"},"userName":{"type":"string"},"dateBirth":{"type":"string","format":"date-time"},"phoneNumber":{"type":"string"},"email":{"type":"string"}},"required":["bank","moneyDuty","lifeOrHouse","apartment","userName","dateBirth","phoneNumber","email"],"additionalProperties":true},"User":{"title":"User","type":"object","properties":{"id":{"type":"number"},"mail":{"type":"string"},"phone_number":{"type":"string"},"password":{"type":"string"},"surname":{"type":"string"},"name":{"type":"string"},"otchestvo":{"type":"string"},"datebirth":{"type":"string","format":"date-time"},"foreigner":{"type":"string"},"document":{"type":"string"},"document_number":{"type":"string"},"document_series":{"type":"string"}},"required":["mail","phone_number","password","surname","name","datebirth","foreigner","document","document_number","document_series"],"additionalProperties":true},"DateType":{},"UserWithRelations":{"title":"UserWithRelations","type":"object","description":"(tsType: UserWithRelations, schemaOptions: { includeRelations: true })","properties":{"id":{"type":"number"},"mail":{"type":"string"},"phone_number":{"type":"string"},"password":{"type":"string"},"surname":{"type":"string"},"name":{"type":"string"},"otchestvo":{"type":"string"},"datebirth":{"type":"string","format":"date-time"},"foreigner":{"type":"string"},"document":{"type":"string"},"document_number":{"type":"string"},"document_series":{"type":"string"}},"required":["mail","phone_number","password","surname","name","datebirth","foreigner","document","document_number","document_series"],"additionalProperties":true,"x-typescript-type":"UserWithRelations"},"UserPartial":{"title":"UserPartial","type":"object","description":"(tsType: Partial<User>, schemaOptions: { partial: true })","properties":{"id":{"type":"number"},"mail":{"type":"string"},"phone_number":{"type":"string"},"password":{"type":"string"},"surname":{"type":"string"},"name":{"type":"string"},"otchestvo":{"type":"string"},"datebirth":{"type":"string","format":"date-time"},"foreigner":{"type":"string"},"document":{"type":"string"},"document_number":{"type":"string"},"document_series":{"type":"string"}},"additionalProperties":true,"x-typescript-type":"Partial<User>"},"PingResponse":{"type":"object","title":"PingResponse","properties":{"greeting":{"type":"string"},"date":{"type":"string"},"url":{"type":"string"},"headers":{"type":"object","properties":{"Content-Type":{"type":"string"}},"additionalProperties":true}}},"loopback.Count":{"type":"object","title":"loopback.Count","x-typescript-type":"@loopback/repository#Count","properties":{"count":{"type":"number"}}},"User.Filter":{"type":"object","title":"User.Filter","properties":{"offset":{"type":"integer","minimum":0},"limit":{"type":"integer","minimum":1,"example":100},"skip":{"type":"integer","minimum":0},"order":{"oneOf":[{"type":"string"},{"type":"array","items":{"type":"string"}}]},"fields":{"oneOf":[{"type":"object","properties":{"id":{"type":"boolean"},"mail":{"type":"boolean"},"phone_number":{"type":"boolean"},"password":{"type":"boolean"},"surname":{"type":"boolean"},"name":{"type":"boolean"},"otchestvo":{"type":"boolean"},"datebirth":{"type":"boolean"},"foreigner":{"type":"boolean"},"document":{"type":"boolean"},"document_number":{"type":"boolean"},"document_series":{"type":"boolean"}},"additionalProperties":true},{"type":"array","items":{"type":"string","example":"id"},"uniqueItems":true}],"title":"User.Fields"}},"additionalProperties":false,"x-typescript-type":"@loopback/repository#Filter<User>"},"User.Filter1":{"type":"object","title":"User.Filter","properties":{"offset":{"type":"integer","minimum":0},"limit":{"type":"integer","minimum":1,"example":100},"skip":{"type":"integer","minimum":0},"order":{"oneOf":[{"type":"string"},{"type":"array","items":{"type":"string"}}]},"where":{"title":"User.WhereFilter","type":"object","additionalProperties":true},"fields":{"oneOf":[{"type":"object","properties":{"id":{"type":"boolean"},"mail":{"type":"boolean"},"phone_number":{"type":"boolean"},"password":{"type":"boolean"},"surname":{"type":"boolean"},"name":{"type":"boolean"},"otchestvo":{"type":"boolean"},"datebirth":{"type":"boolean"},"foreigner":{"type":"boolean"},"document":{"type":"boolean"},"document_number":{"type":"boolean"},"document_series":{"type":"boolean"}},"additionalProperties":true},{"type":"array","items":{"type":"string","example":"id"},"uniqueItems":true}],"title":"User.Fields"}},"additionalProperties":false,"x-typescript-type":"@loopback/repository#Filter<User>"}}}}